README.md
setup.cfg
setup.py
pygamepp/__init__.py
pygamepp/block.py
pygamepp/game.py
pygamepp/game_object.py
pygamepp/grid.py
pygamepp/grid_game_object.py
pygamepp/main.py
pygamepp.egg-info/PKG-INFO
pygamepp.egg-info/SOURCES.txt
pygamepp.egg-info/dependency_links.txt
pygamepp.egg-info/requires.txt
pygamepp.egg-info/top_level.txt