Metadata-Version: 1.1
Name: pygamepp
Version: 0.11
Summary: This is a wrapper i made for pygame for my schoool projects
Home-page: UNKNOWN
Author: Hadar Dagan
Author-email: hadarda11@gmail.com
License: UNKNOWN
Download-URL: https://github.com/hadar759/pygamepp/archive/v_011.tar.gz
Platform: UNKNOWN
